<?xml version="1.0" encoding="utf-8"?>
<Application>
  <Views Id="Views">
    <DetailView Id="EquipmentFileMaintenance_DetailView">
      <Layout Id="Layout">
        <LayoutGroup Id="Main">
          <LayoutGroup Id="SimpleEditors">
            <LayoutGroup Id="EquipmentFileMaintenance">
              <LayoutGroup Id="EquipmentFileMaintenance_col2">
                <LayoutItem Id="EquipmentChildrenClasses" RelativeSize="94.6774193548387" />
              </LayoutGroup>
            </LayoutGroup>
          </LayoutGroup>
        </LayoutGroup>
      </Layout>
    </DetailView>
  </Views>
</Application>